polysh/__init__.py
polysh/buffered_dispatcher.py
polysh/callbacks.py
polysh/completion.py
polysh/console.py
polysh/control_commands.py
polysh/control_commands_helpers.py
polysh/dispatchers.py
polysh/display_names.py
polysh/host_syntax.py
polysh/main.py
polysh/remote_dispatcher.py
polysh/stdin.py
polysh/terminal_size.py
polysh-0.13.dist-info/LICENSE
polysh-0.13.dist-info/METADATA
polysh-0.13.dist-info/WHEEL
polysh-0.13.dist-info/entry_points.txt
polysh-0.13.dist-info/top_level.txt
polysh-0.13.dist-info/RECORD
