Metadata-Version: 2.1
Name: polysh
Version: 0.13
Summary: Control thousands of ssh sesions from a single prompt
Home-page: http://github.com/innogames/polysh/
Maintainer: InnoGames System Administration
Maintainer-email: it@innogames.com
License: UNKNOWN
Keywords: gsh group shell cluster ssh multiplexer
Platform: UNKNOWN
Classifier: Intended Audience :: System Administrators
Classifier: Intended Audience :: Developers
Classifier: Topic :: System :: Systems Administration
Classifier: Topic :: System :: Shells
Classifier: Topic :: System :: Clustering
Classifier: Topic :: System :: Distributed Computing
Classifier: Environment :: Console
Classifier: Operating System :: POSIX :: Linux
Classifier: Operating System :: MacOS :: MacOS X
Classifier: License :: OSI Approved :: GNU General Public License v2 or later (GPLv2+)
Classifier: Development Status :: 5 - Production/Stable
Classifier: Programming Language :: Python :: 3
Classifier: Programming Language :: Python :: 3.5
Classifier: Programming Language :: Python :: 3.6
Requires-Python: >=3.5
